calcoolator/__init__.py
calcoolator/base_class.py
calcoolator/handler_class.py
calcoolator/exceptions/__init__.py
calcoolator/exceptions/negative_root.py
calcoolator-0.0.8.dist-info/METADATA
calcoolator-0.0.8.dist-info/WHEEL
calcoolator-0.0.8.dist-info/licenses/LICENSE
calcoolator-0.0.8.dist-info/RECORD
