Metadata-Version: 2.3
Name: calcoolator
Version: 0.0.8
Summary: Simple calculator project
Project-URL: Homepage, https://github.com/berto-polo
Author-email: Berto Polo <bertopolo@gmail.com>
License-File: LICENSE
Keywords: calculator,newbie
Classifier: License :: OSI Approved :: MIT License
Classifier: Operating System :: OS Independent
Classifier: Programming Language :: Python :: 3
Requires-Python: >=3.8
